extend/__init__.py
extend/__version__.py
extend/client.py
extend/extend.py
extend/models.py
extend/validations.py
extend/config/__init__.py
extend/config/config_prod.py
extend/config/config_stage.py
extend/resources/__init__.py
extend/resources/credit_cards.py
extend/resources/expense_data.py
extend/resources/receipt_attachments.py
extend/resources/receipt_capture.py
extend/resources/resource.py
extend/resources/transactions.py
extend/resources/virtual_cards.py
paywithextend-1.2.2.dist-info/METADATA
paywithextend-1.2.2.dist-info/WHEEL
paywithextend-1.2.2.dist-info/licenses/LICENSE
paywithextend-1.2.2.dist-info/licenses/LICENSE.bak
paywithextend-1.2.2.dist-info/RECORD
