Metadata-Version: 2.4
Name: paywithextend
Version: 1.2.2
Summary: Python client for the Extend API
Project-URL: Issue Tracker, https://github.com/paywithextend/extend-python/issues
Project-URL: Source Code, https://github.com/paywithextend/extend-python
Author-email: Extend Engineering <support@paywithextend.com>
License: MIT
License-File: LICENSE
License-File: LICENSE.bak
Classifier: License :: OSI Approved :: MIT License
Classifier: Operating System :: OS Independent
Classifier: Programming Language :: Python :: 3
Requires-Python: >=3.8
Requires-Dist: build
Requires-Dist: httpx>=0.24.0
Requires-Dist: python-dotenv==1.0.1
Requires-Dist: typing-extensions>=4.0.0
Provides-Extra: dev
Requires-Dist: black>=23.0; extra == 'dev'
Requires-Dist: ipykernel>=6.0.0; extra == 'dev'
Requires-Dist: isort>=5.0; extra == 'dev'
Requires-Dist: jupyter>=1.0.0; extra == 'dev'
Requires-Dist: notebook>=7.0.0; extra == 'dev'
Requires-Dist: pytest-asyncio>=0.21.0; extra == 'dev'
Requires-Dist: pytest-cov>=4.0; extra == 'dev'
Requires-Dist: pytest-mock==3.14.0; extra == 'dev'
Requires-Dist: pytest>=7.0; extra == 'dev'
